nbs2ctx/__init__.py
nbs2ctx/_modidx.py
nbs2ctx/core.py
nbs2ctx-0.0.2.dist-info/licenses/LICENSE
nbs2ctx-0.0.2.dist-info/METADATA
nbs2ctx-0.0.2.dist-info/WHEEL
nbs2ctx-0.0.2.dist-info/entry_points.txt
nbs2ctx-0.0.2.dist-info/top_level.txt
nbs2ctx-0.0.2.dist-info/RECORD
